chainlit/__init__.py
chainlit/__main__.py
chainlit/_utils.py
chainlit/action.py
chainlit/auth/__init__.py
chainlit/auth/cookie.py
chainlit/auth/jwt.py
chainlit/cache.py
chainlit/callbacks.py
chainlit/chat_context.py
chainlit/chat_settings.py
chainlit/cli/__init__.py
chainlit/config.py
chainlit/context.py
chainlit/copilot/dist/index.js
chainlit/data/__init__.py
chainlit/data/acl.py
chainlit/data/base.py
chainlit/data/chainlit_data_layer.py
chainlit/data/dynamodb.py
chainlit/data/literalai.py
chainlit/data/sql_alchemy.py
chainlit/data/storage_clients/__init__.py
chainlit/data/storage_clients/azure.py
chainlit/data/storage_clients/azure_blob.py
chainlit/data/storage_clients/base.py
chainlit/data/storage_clients/gcs.py
chainlit/data/storage_clients/s3.py
chainlit/data/utils.py
chainlit/discord/__init__.py
chainlit/discord/app.py
chainlit/element.py
chainlit/emitter.py
chainlit/frontend/dist/assets/DailyMotion-rF7k-fQA.js
chainlit/frontend/dist/assets/DailyMotion-rF7k-fQA.js.map
chainlit/frontend/dist/assets/Dataframe-B_wlBH7S.js
chainlit/frontend/dist/assets/Dataframe-B_wlBH7S.js.map
chainlit/frontend/dist/assets/Facebook-DO90ZZuM.js
chainlit/frontend/dist/assets/Facebook-DO90ZZuM.js.map
chainlit/frontend/dist/assets/FilePlayer-K9gYvUk2.js
chainlit/frontend/dist/assets/FilePlayer-K9gYvUk2.js.map
chainlit/frontend/dist/assets/Kaltura-D3G4bmQI.js
chainlit/frontend/dist/assets/Kaltura-D3G4bmQI.js.map
chainlit/frontend/dist/assets/Mixcloud-Bwxjjxu5.js
chainlit/frontend/dist/assets/Mixcloud-Bwxjjxu5.js.map
chainlit/frontend/dist/assets/Mux-BU32YZuN.js
chainlit/frontend/dist/assets/Mux-BU32YZuN.js.map
chainlit/frontend/dist/assets/Preview-Di8xmjNw.js
chainlit/frontend/dist/assets/Preview-Di8xmjNw.js.map
chainlit/frontend/dist/assets/SoundCloud-JrB1cYVD.js
chainlit/frontend/dist/assets/SoundCloud-JrB1cYVD.js.map
chainlit/frontend/dist/assets/Streamable-JEdHy-d5.js
chainlit/frontend/dist/assets/Streamable-JEdHy-d5.js.map
chainlit/frontend/dist/assets/Twitch-B9_3p6BU.js
chainlit_hl_custom-2.6.2.dist-info/METADATA
chainlit_hl_custom-2.6.2.dist-info/WHEEL
chainlit_hl_custom-2.6.2.dist-info/entry_points.txt
chainlit_hl_custom-2.6.2.dist-info/RECORD
